kleiven/__init__.py
kleiven/azure/__init__.py
kleiven/azure/storage/__init__.py
kleiven/azure/storage/blob_service.py
kleiven/azure/storage/blob_storage.py
kleiven/azure/storage/queue.py
kleiven/azure/storage/queue_service.py
kleiven/azure/storage/table_service.py
kleiven/azure/storage/table_storage.py
kleiven_azure_storage-0.0.3.dist-info/licenses/LICENSE
kleiven_azure_storage-0.0.3.dist-info/METADATA
kleiven_azure_storage-0.0.3.dist-info/WHEEL
kleiven_azure_storage-0.0.3.dist-info/top_level.txt
kleiven_azure_storage-0.0.3.dist-info/RECORD
