Metadata-Version: 2.4
Name: kleiven-azure-storage
Version: 0.0.3
Summary: Wraps Azure SDK to keep common operations short and consistent.
Author: "Eivind Kleiven"
Requires-Python: >=3.10
License-File: LICENSE
Requires-Dist: python-dotenv
Requires-Dist: azure-data-tables
Requires-Dist: azure-storage-blob
Requires-Dist: azure-storage-queue
Dynamic: license-file
